sklearmmm/__init__.py
sklearmmm/images/001_1.png
sklearmmm/images/001_2.png
sklearmmm/images/002_1.png
sklearmmm/images/002_2.png
sklearmmm/images/003_1.png
sklearmmm/images/003_2.png
sklearmmm/images/004_1.png
sklearmmm/images/004_2.png
sklearmmm/images/005_1.png
sklearmmm/images/005_2.png
sklearmmm/images/005_3.png
sklearmmm/images/006_1.png
sklearmmm/images/006_2.png
sklearmmm/images/007_1.png
sklearmmm/images/007_2.png
sklearmmm/images/008_1.png
sklearmmm/images/008_2.png
sklearmmm/images/009_1.png
sklearmmm/images/009_2.png
sklearmmm/images/010_1.png
sklearmmm/images/010_2.png
sklearmmm/images/011_1.png
sklearmmm/images/012_1.png
sklearmmm/images/012_2.png
sklearmmm/images/013_1.png
sklearmmm/images/013_2.png
sklearmmm/images/014_1.png
sklearmmm/images/015_1.png
sklearmmm/images/016_1.png
sklearmmm/images/017_1.png
sklearmmm/images/017_2.png
sklearmmm/images/018_1.png
sklearmmm/images/019_1.png
sklearmmm/images/019_2.png
sklearmmm/images/020_1.png
sklearmmm/images/020_2.png
sklearmmm/images/020_3.png
sklearmmm/images/021_1.png
sklearmmm/images/022_1.png
sklearmmm/images/022_2.png
sklearmmm/images/022_3.png
sklearmmm/images/023_1.png
sklearmmm/images/023_2.png
sklearmmm/images/024_1.png
sklearmmm/images/024_2.png
sklearmmm/images/025_1.png
sklearmmm/images/026_1.png
sklearmmm/images/027_1.png
sklearmmm/images/028_1.png
sklearmmm/images/029_1.png
sklearmmm/images/030_1.png
sklearmmm/images/030_2.png
sklearmmm/images/031_1.png
sklearmmm/images/031_2.png
sklearmmm/images/031_3.png
sklearmmm/images/032_1.png
sklearmmm/images/032_2.png
sklearmmm/images/032_3.png
sklearmmm/images/033_1.png
sklearmmm/images/034_1.png
sklearmmm/images/034_2.png
sklearmmm/images/035_1.png
sklearmmm/images/035_2.png
sklearmmm/images/036_1.png
sklearmmm/images/036_2.png
sklearmmm/images/037_1.png
sklearmmm/images/037_2.png
sklearmmm/images/037_3.png
sklearmmm/images/037_4.png
sklearmmm/images/038_1.png
sklearmmm/images/039_1.png
sklearmmm/images/039_2.png
sklearmmm/images/040_1.png
sklearmmm-0.3.0.2.dist-info/METADATA
sklearmmm-0.3.0.2.dist-info/WHEEL
sklearmmm-0.3.0.2.dist-info/top_level.txt
sklearmmm-0.3.0.2.dist-info/RECORD
