Metadata-Version: 2.1
Name: sklearmmm
Version: 0.3.0.2
Summary: Library with get_task function
Home-page: https://github.com/johndoe/sklearmmm
Author: John Doe
Author-email: johndoe@gmail.com
License: MIT
Classifier: Programming Language :: Python :: 3
Classifier: License :: OSI Approved :: MIT License
Classifier: Operating System :: OS Independent
Requires-Python: >=3.6
